enhancedpolars/__init__.py
enhancedpolars/_version.py
enhancedpolars/base.py
enhancedpolars/cohorts.py
enhancedpolars/epl.py
enhancedpolars/groupby.py
enhancedpolars/indexing.py
enhancedpolars/interpolation.py
enhancedpolars/io.py
enhancedpolars/merging.py
enhancedpolars/ml_pipeline.py
enhancedpolars/pyarrow_typing.py
enhancedpolars/register.py
enhancedpolars/series.py
enhancedpolars/time_integration.py
enhancedpolars/to_sql.py
enhancedpolars/Stats/__init__.py
enhancedpolars/Stats/descriptive_stats.py
enhancedpolars/Stats/hypothesis_tests.py
enhancedpolars/Stats/random_sampling.py
enhancedpolars-0.0.4.dist-info/METADATA
enhancedpolars-0.0.4.dist-info/WHEEL
enhancedpolars-0.0.4.dist-info/licenses/LICENSE
enhancedpolars-0.0.4.dist-info/RECORD
