Metadata-Version: 2.4
Name: EnhancedPolars
Version: 0.0.4
Summary: Enhanced utilities for Polars DataFrames
License: MIT
License-File: LICENSE
Requires-Python: >=3.12
Requires-Dist: coreutilities<2.0.0,>=0.0.6
Requires-Dist: joblib<2.0.0,>=1.5.0
Requires-Dist: numpy<3.0.0,>=2.3.0
Requires-Dist: pandas<3.0.0,>=2.3.0
Requires-Dist: polars<2.0.0,>=1.33.0
Requires-Dist: pyarrow<25.0.0,>=21.0.0
Requires-Dist: python-dateutil<3.0.0,>=2.9.0
Requires-Dist: sqlutilities<2.0.0,>=0.1.1
Requires-Dist: tqdm<5.0.0,>=4.67.0
Provides-Extra: all
Requires-Dist: scikit-learn<2.0.0,>=1.7.0; extra == 'all'
Requires-Dist: scipy<2.0.0,>=1.16.0; extra == 'all'
Provides-Extra: ml
Requires-Dist: scikit-learn<2.0.0,>=1.7.0; extra == 'ml'
Provides-Extra: sci
Requires-Dist: scipy<2.0.0,>=1.16.0; extra == 'sci'
